{"id":"11348282","source":"twitter","word_count":44494,"processed_lang":"en","tree":{"id":"r","name":"root","children":[{"id":"personality","name":"Big 5","children":[{"id":"Neuroticism_parent","name":"Emotional range","category":"personality","percentage":0.03549752441415065,"children":[{"id":"Openness","name":"Openness","category":"personality","percentage":0.8897085726357665,"sampling_error":0.03949711,"children":[{"id":"Adventurousness","name":"Adventurousness","category":"personality","percentage":0.9395258242919805,"sampling_error":0.03311216},{"id":"Artistic interests","name":"Artistic interests","category":"personality","percentage":0.5295321783737851,"sampling_error":0.0692239},{"id":"Emotionality","name":"Emotionality","category":"personality","percentage":0.03149243769147465,"sampling_error":0.02634522},{"id":"Imagination","name":"Imagination","category":"personality","percentage":0.8321751853859903,"sampling_error":0.04457761},{"id":"Intellect","name":"Intellect","category":"personality","percentage":0.9395495641431725,"sampling_error":0.03829571},{"id":"Liberalism","name":"Authority-challenging","category":"personality","percentage":0.9138023794542789,"sampling_error":0.06873399}]},{"id":"Conscientiousness","name":"Conscientiousness","category":"personality","percentage":0.9245906296810452,"sampling_error":0.05549541,"children":[{"id":"Achievement striving","name":"Achievement striving","category":"personality","percentage":0.8649780007685708,"sampling_error":0.06905805},{"id":"Cautiousness","name":"Cautiousness","category":"personality","percentage":0.8989388583462486,"sampling_error":0.05942426},{"id":"Dutifulness","name":"Dutifulness","category":"personality","percentage":0.9436427041100466,"sampling_error":0.03374364},{"id":"Orderliness","name":"Orderliness","category":"personality","percentage":0.37325770941358033,"sampling_error":0.04575811},{"id":"Self-discipline","name":"Self-discipline","category":"personality","percentage":0.9346213833725365,"sampling_error":0.0441163},{"id":"Self-efficacy","name":"Self-efficacy","category":"personality","percentage":0.9710888605117015,"sampling_error":0.07220646}]},{"id":"Extraversion","name":"Extraversion","category":"personality","percentage":0.1153428690269922,"sampling_error":0.03830742,"children":[{"id":"Activity level","name":"Activity level","category":"personality","percentage":0.7458994839533123,"sampling_error":0.05123428},{"id":"Assertiveness","name":"Assertiveness","category":"personality","percentage":0.10875044080085439,"sampling_error":0.05779381},{"id":"Cheerfulness","name":"Cheerfulness","category":"personality","percentage":0.08550668104830308,"sampling_error":0.07579733},{"id":"Excitement-seeking","name":"Excitement-seeking","category":"personality","percentage":0.05404823146068695,"sampling_error":0.06495101},{"id":"Friendliness","name":"Outgoing","category":"personality","percentage":0.5124628408784003,"sampling_error":0.06065659},{"id":"Gregariousness","name":"Gregariousness","category":"personality","percentage":0.09487566230846561,"sampling_error":0.04096594}]},{"id":"Agreeableness","name":"Agreeableness","category":"personality","percentage":0.4209021422904009,"sampling_error":0.07650298,"children":[{"id":"Altruism","name":"Altruism","category":"personality","percentage":0.8803631767747692,"sampling_error":0.04831168},{"id":"Cooperation","name":"Cooperation","category":"personality","percentage":0.962521810449404,"sampling_error":0.06519076},{"id":"Modesty","name":"Modesty","category":"personality","percentage":0.32138274936471645,"sampling_error":0.03935304},{"id":"Morality","name":"Uncompromising","category":"personality","percentage":0.8140720934793767,"sampling_error":0.04512489},{"id":"Sympathy","name":"Sympathy","category":"personality","percentage":0.8082906422266329,"sampling_error":0.07938574},{"id":"Trust","name":"Trust","category":"personality","percentage":0.9441723628835162,"sampling_error":0.03168323}]},{"id":"Neuroticism","name":"Emotional range","category":"personality","percentage":0.03549752441415065,"sampling_error":0.07508171,"children":[{"id":"Anger","name":"Fiery","category":"personality","percentage":0.013523275897372723,"sampling_error":0.07343766},{"id":"Anxiety","name":"Prone to worry","category":"personality","percentage":0.00994425693869029,"sampling_error":0.03550205},{"id":"Depression","name":"Melancholy","category":"personality","percentage":0.041270786796267736,"sampling_error":0.03784732},{"id":"Immoderation","name":"Immoderation","category":"personality","percentage":0.04784138991857134,"sampling_error":0.0443366},{"id":"Self-consciousness","name":"Self-consciousness","category":"personality","percentage":0.10158565028444833,"sampling_error":0.03823971},{"id":"Vulnerability","name":"Susceptible to stress","category":"personality","percentage":0.13391436423457828,"sampling_error":0.06344788}]}]}]},{"id":"needs","name":"Needs","children":[{"id":"Self-expression_parent","name":"Self-expression","category":"needs","percentage":0.016454859345363296,"children":[{"id":"Challenge","name":"Challenge","category":"needs","percentage":0.02877986276816491,"sampling_error":0.05187795},{"id":"Closeness","name":"Closeness","category":"needs","percentage":0.030335471054758097,"sampling_error":0.05335254},{"id":"Curiosity","name":"Curiosity","category":"needs","percentage":0.048259928263765337,"sampling_error":0.07487604},{"id":"Excitement","name":"Excitement","category":"needs","percentage":0.018810864593385268,"sampling_error":0.07021598},{"id":"Harmony","name":"Harmony","category":"needs","percentage":0.1426120645767368,"sampling_error":0.06684309},{"id":"Ideal","name":"Ideal","category":"needs","percentage":0.016650596081957836,"sampling_error":0.06705341},{"id":"Liberty","name":"Liberty","category":"needs","percentage":0.026590617435889315,"sampling_error":0.09415605},{"id":"Love","name":"Love","category":"needs","percentage":0.08493677452246001,"sampling_error":0.06097935},{"id":"Practicality","name":"Practicality","category":"needs","percentage":0.07866988835942978,"sampling_error":0.05643147},{"id":"Self-expression","name":"Self-expression","category":"needs","percentage":0.016454859345363296,"sampling_error":0.05075313},{"id":"Stability","name":"Stability","category":"needs","percentage":0.02503319688989893,"sampling_error":0.06987196},{"id":"Structure","name":"Structure","category":"needs","percentage":0.031212826795944098,"sampling_error":0.05206323}]}]},{"id":"values","name":"Values","children":[{"id":"Self-enhancement_parent","name":"Self-enhancement","category":"values","percentage":0.03196287834660757,"children":[{"id":"Conservation","name":"Conservation","category":"values","percentage":0.8768226101397728,"sampling_error":0.05969291},{"id":"Openness to change","name":"Openness to change","category":"values","percentage":0.7521100622907343,"sampling_error":0.05736528},{"id":"Hedonism","name":"Hedonism","category":"values","percentage":0.3245054184518836,"sampling_error":0.08357843},{"id":"Self-enhancement","name":"Self-enhancement","category":"values","percentage":0.03196287834660757,"sampling_error":0.06159357},{"id":"Self-transcendence","name":"Self-transcendence","category":"values","percentage":0.4215829562574231,"sampling_error":0.04417373}]}]},{"id":"sbh","name":"Social Behavior","category":"behavior","children":[{"id":"sbh_parent","name":"Fri. Evening","category":"behavior","children":[{"id":"Friday_parent","name":"Fri.","category":"behavior","percentage":0.17307026652821045,"children":[{"id":"Sunday","name":"Sunday","category":"behavior","percentage":0.10522672204915196},{"id":"Monday","name":"Monday","category":"behavior","percentage":0.1526479750778816},{"id":"Tuesday","name":"Tuesday","category":"behavior","percentage":0.13776393215645552},{"id":"Wednesday","name":"Wednesday","category":"behavior","percentage":0.1536863966770509},{"id":"Thursday","name":"Thursday","category":"behavior","percentage":0.16614745586708204},{"id":"Friday","name":"Friday","category":"behavior","percentage":0.17307026652821045},{"id":"Saturday","name":"Saturday","category":"behavior","percentage":0.11145725164416753}]},{"id":"8:00 pm_parent","name":"Evening","category":"behavior","percentage":0.08168916580131533,"children":[{"id":"0:00 am","name":"0:00 am","category":"behavior","percentage":0.060228452751817235},{"id":"1:00 am","name":"1:00 am","category":"behavior","percentage":0.05019037729318103},{"id":"2:00 am","name":"2:00 am","category":"behavior","percentage":0.03946002076843198},{"id":"3:00 am","name":"3:00 am","category":"behavior","percentage":0.02561439944617515},{"id":"4:00 am","name":"4:00 am","category":"behavior","percentage":0.012461059190031152},{"id":"5:00 am","name":"5:00 am","category":"behavior","percentage":0.006230529595015576},{"id":"6:00 am","name":"6:00 am","category":"behavior","percentage":0.005538248528902735},{"id":"7:00 am","name":"7:00 am","category":"behavior","percentage":0.005538248528902735},{"id":"8:00 am","name":"8:00 am","category":"behavior","percentage":0.0024229837313949464},{"id":"9:00 am","name":"9:00 am","category":"behavior","percentage":0.004845967462789893},{"id":"10:00 am","name":"10:00 am","category":"behavior","percentage":0.012461059190031152},{"id":"11:00 am","name":"11:00 am","category":"behavior","percentage":0.012807199723087574},{"id":"12:00 pm","name":"12:00 pm","category":"behavior","percentage":0.013845621322256836},{"id":"1:00 pm","name":"1:00 pm","category":"behavior","percentage":0.02596053997923157},{"id":"2:00 pm","name":"2:00 pm","category":"behavior","percentage":0.0512287988923503},{"id":"3:00 pm","name":"3:00 pm","category":"behavior","percentage":0.06161301488404292},{"id":"4:00 pm","name":"4:00 pm","category":"behavior","percentage":0.07199723087573555},{"id":"5:00 pm","name":"5:00 pm","category":"behavior","percentage":0.0792661820699204},{"id":"6:00 pm","name":"6:00 pm","category":"behavior","percentage":0.07857390100380754},{"id":"7:00 pm","name":"7:00 pm","category":"behavior","percentage":0.08030460366908965},{"id":"8:00 pm","name":"8:00 pm","category":"behavior","percentage":0.08168916580131533},{"id":"9:00 pm","name":"9:00 pm","category":"behavior","percentage":0.07476635514018691},{"id":"10:00 pm","name":"10:00 pm","category":"behavior","percentage":0.07130494980962271},{"id":"11:00 pm","name":"11:00 pm","category":"behavior","percentage":0.07165109034267912}]}]}]}]}}